{
    "data": [
        {
            "id": 1,
            "value": "https://picsum.photos/id/947/200/300?type=post"
        },
        {
            "id": 2,
            "value": "https://picsum.photos/id/979/200/300?type=post"
        },
        {
            "id": 3,
            "value": "https://picsum.photos/id/289/200/300?type=post"
        },
        {
            "id": 4,
            "value": "https://picsum.photos/id/454/200/300?type=post"
        },
        {
            "id": 5,
            "value": "https://picsum.photos/id/422/200/300?type=post"
        },
        {
            "id": 6,
            "value": "https://picsum.photos/id/773/200/300?type=post"
        },
        {
            "id": 7,
            "value": "https://picsum.photos/id/588/200/300?type=post"
        },
        {
            "id": 8,
            "value": "https://picsum.photos/id/709/200/300?type=post"
        },
        {
            "id": 9,
            "value": "https://picsum.photos/id/627/200/300?type=post"
        }
    ],
    "description": "This is some sample data for some node, that is consumed over the API",
    "expires_on": "2024-03-20 00:37:43.351573",
    "node": "post",
    "scheme": "node",
    "updated_on": "2024-03-20 00:37:23.351575",
    "version": "v3.1.44"
}