{
    "data": [
        {
            "id": 1,
            "value": "https://picsum.photos/id/972/200/300?type=post"
        },
        {
            "id": 2,
            "value": "https://picsum.photos/id/167/200/300?type=post"
        },
        {
            "id": 3,
            "value": "https://picsum.photos/id/69/200/300?type=post"
        },
        {
            "id": 4,
            "value": "https://picsum.photos/id/87/200/300?type=post"
        },
        {
            "id": 5,
            "value": "https://picsum.photos/id/112/200/300?type=post"
        },
        {
            "id": 6,
            "value": "https://picsum.photos/id/158/200/300?type=post"
        },
        {
            "id": 7,
            "value": "https://picsum.photos/id/776/200/300?type=post"
        },
        {
            "id": 8,
            "value": "https://picsum.photos/id/917/200/300?type=post"
        },
        {
            "id": 9,
            "value": "https://picsum.photos/id/574/200/300?type=post"
        }
    ],
    "description": "This is some sample data for some node, that is consumed over the API",
    "expires_on": "2024-03-20 00:47:16.650933",
    "node": "post",
    "scheme": "node",
    "updated_on": "2024-03-20 00:46:56.650935",
    "version": "v8.4.60"
}